Curp-2.0.dist-info/top_level.txt
Curp-2.0.dist-info/METADATA
Curp-2.0.dist-info/entry_points.txt
Curp-2.0.dist-info/WHEEL
Curp-2.0.dist-info/LICENSE.txt
Curp-2.0.dist-info/RECORD
curp/setting_base.py
curp/_version.py
curp/compute.py
curp/__init__.py
curp/utility.py
curp/exception.py
curp/clog.py
curp/parallel.py
curp/console.py
curp/setting.py
curp/LICENSE-short.txt
curp/tool/cal_diffec.py
curp/tool/conv_labels.py
curp/tool/plot_ec_average.py
curp/tool/__init__.py
curp/tool/renum_residue.py
curp/tool/conv_BW.py
curp/tool/count_neighbor.py
curp/tool/console.py
curp/tool/plot_ec_time.py
curp/tool/sele/sel_noneighbor.py
curp/tool/sele/sel_noasa.py
curp/tool/sele/sel_noloop.py
curp/tool/sele/sel_nocap.py
curp/tool/sele/__init__.py
curp/tool/sele/sel_neighbor.py
curp/tool/sele/sel_helix.py
curp/tool/sele/console.py
curp/tool/sele/sel_thresh.py
curp/tool/sele/sel_nohelix.py
curp/forcefield/amberbase.py
curp/forcefield/__init__.py
curp/forcefield/lib_nonbond.cpython-36m-x86_64-linux-gnu.so
curp/forcefield/lib_bonded_pair.cpython-36m-x86_64-linux-gnu.so
curp/twobody/lib_amberbase.cpython-36m-x86_64-linux-gnu.so
curp/twobody/amberbase.py
curp/twobody/__init__.py
curp/dynamics/integrator.py
curp/dynamics/__init__.py
curp/dynamics/writer.py
curp/script/split_interval.py
curp/script/pickup_respairs_par.py
curp/script/cal_tc_bypair.py
curp/script/lib_acf.cpython-36m-x86_64-linux-gnu.so
curp/script/adjustvel.py
curp/script/__init__.py
curp/script/lib_hfacf.cpython-36m-x86_64-linux-gnu.so
curp/script/average_tensor.py
curp/script/cal_tc.py
curp/script/graph_een.py
curp/script/distance.py
curp/script/conv_trj.py
curp/script/pdb_.py
curp/script/lib_distance.cpython-36m-x86_64-linux-gnu.so
curp/script/view_ec.py
curp/script/console.py
curp/script/mask.py
curp/script/sum_acf.py
curp/script/analyze/get_ncdata.py
curp/script/analyze/pickup_respairs.py
curp/script/analyze/lib_pickup.cpython-36m-x86_64-linux-gnu.so
curp/script/analyze/__init__.py
curp/script/analyze/divide_flux.py
curp/script/analyze/simplify_tensor.py
curp/script/analyze/sum_tc.py
curp/parser/trans_rot.py
curp/parser/__init__.py
