Metadata-Version: 2.1
Name: Curp
Version: 2.0
Summary: Inter-residue Current calculation in Proteins from MD             trajectory
Home-page: https://github.com/yamatolab/current-calculations-for-proteins
Author: Yamato's Lab
Author-email: yamato@nagoya-u.jp
License: UNKNOWN
Platform: UNKNOWN
Classifier: Development Status :: 5 - Production/Stable
Classifier: Intended Audience :: Science/Research
Classifier: Operating System :: MacOS
Classifier: Operating System :: POSIX :: Linux
Classifier: Programming Language :: Python :: 3
Classifier: Programming Language :: Python :: 3.6
Classifier: Programming Language :: Fortran
Classifier: Topic :: Scientific/Engineering
Classifier: Topic :: Scientific/Engineering :: Bio-Informatics
Classifier: Topic :: Scientific/Engineering :: Physics
Classifier: Topic :: Scientific/Engineering :: Chemistry
Requires-Python: >3.5,<3.7
License-File: LICENSE.txt
Requires-Dist: numpy (<1.17,>=1.11.2)
Requires-Dist: nose (==1.3.7)
Requires-Dist: mpi4py (>=1.2)
Requires-Dist: pygraphviz (<1.6,>1.2)
Requires-Dist: netcdf4 (<1.7,>=1.4.2)
Provides-Extra: dev
Requires-Dist: benchmarker (<5,>=4.0) ; extra == 'dev'
